fireorm/__init__.py
fireorm/Fields/BooleanField.py
fireorm/Fields/DateField.py
fireorm/Fields/Field.py
fireorm/Fields/ListField.py
fireorm/Fields/MapField.py
fireorm/Fields/NestedModel.py
fireorm/Fields/NullField.py
fireorm/Fields/NumberField.py
fireorm/Fields/ReferenceField.py
fireorm/Fields/TextField.py
fireorm/Fields/__init__.py
fireorm/Models/DateModel.py
fireorm/Models/Model.py
fireorm/Models/__init__.py
fireorm/Queries/Query.py
fireorm/Queries/__init__.py
fireorm/database/Database.py
fireorm/database/__init__.py
fireorm/utils/__init__.py
fireorm/utils/make_update_obj.py
fireorm-0.0.14.dist-info/LICENSE
fireorm-0.0.14.dist-info/METADATA
fireorm-0.0.14.dist-info/WHEEL
fireorm-0.0.14.dist-info/top_level.txt
fireorm-0.0.14.dist-info/RECORD
